SRPFITS/GetFWHM.py
SRPFITS/SRPFITSPath.py
SRPFITS/__init__.py
SRPFITS/Data/.DS_Store
SRPFITS/Data/SExtractor/SRPConvIn
SRPFITS/Data/SExtractor/SRPConvLSLASCIn
SRPFITS/Data/SExtractor/SRPNnwIn
SRPFITS/Data/SExtractor/SRPParamIn
SRPFITS/Data/SExtractor/SRPSexIn
SRPFITS/Data/SExtractor/SRPSexLSLASCIn
SRPFITS/Data/SExtractor/SRPSexREMREMIRIn
SRPFITS/Data/SExtractor/SRPSexREMROS2In
SRPFITS/Data/SExtractor/SRPSexREMROSSIn
SRPFITS/Data/SExtractor/SRPSexTNGLRSIn
SRPFITS/Fits/AddHeaderComment.py
SRPFITS/Fits/AddHeaderEntry.py
SRPFITS/Fits/FitsConstants.py
SRPFITS/Fits/FitsImageClass.py
SRPFITS/Fits/FitsTabsAppend.py
SRPFITS/Fits/GetData.py
SRPFITS/Fits/GetHeader.py
SRPFITS/Fits/GetHeaderValue.py
SRPFITS/Fits/GetSpectrum.py
SRPFITS/Fits/GetSpectrumPosition.py
SRPFITS/Fits/GetWCS.py
SRPFITS/Fits/IsFits.py
SRPFITS/Fits/WCSPixelScale.py
SRPFITS/Fits/WCSRotationDeg.py
SRPFITS/Fits/__init__.py
SRPFITS/Frames/AstrometryClass.py
SRPFITS/Frames/DAOObjectClass.py
SRPFITS/Frames/EclipseConstants.py
SRPFITS/Frames/EclipseObjectClass.py
SRPFITS/Frames/Pixel2WCS.py
SRPFITS/Frames/SExtractorConstants.py
SRPFITS/Frames/SexConstants.py
SRPFITS/Frames/SexObjectClass.py
SRPFITS/Frames/SourceObjectsClass.py
SRPFITS/Frames/WCS2Pixel.py
SRPFITS/Frames/__init__.py
SRPFITS/Frames/getCenterRADEC.py
SRPFITS/Math/TriangleMatch.py
SRPFITS/Math/__init__.py
SRPFITS/Photometry/ApErr.py
SRPFITS/Photometry/ApyPhot.py
SRPFITS/Photometry/Counts2Mag.py
SRPFITS/Photometry/DaoPhot.py
SRPFITS/Photometry/FitsPhotometryClass.py
SRPFITS/Photometry/Mag2Counts.py
SRPFITS/Photometry/MinMax.py
SRPFITS/Photometry/__init__.py
SRPFITS/Photometry/centerGauss.py
SRPFITS/Photometry/centerMoment.py
SRPFITS/Photometry/centerObj.py
SRPFITS/Photometry/getBackground.py
SRPFITS/Photometry/resid.py
srpastro_fits-3.0.10.data/scripts/SRPAdvAverage
srpastro_fits-3.0.10.data/scripts/SRPAlignImaging
srpastro_fits-3.0.10.data/scripts/SRPAstrometry
srpastro_fits-3.0.10.data/scripts/SRPAverage
srpastro_fits-3.0.10.data/scripts/SRPBias
srpastro_fits-3.0.10.dist-info/licenses/LICENSE.txt
srpastro_fits-3.0.10.dist-info/METADATA
srpastro_fits-3.0.10.dist-info/WHEEL
srpastro_fits-3.0.10.dist-info/top_level.txt
srpastro_fits-3.0.10.dist-info/RECORD
